epigeec_ihecmetadata/__init__.py
epigeec_ihecmetadata/ihecmetadata.py
epigeec_ihecmetadata/converter/__init__.py
epigeec_ihecmetadata/converter/legacyconverter.py
epigeec_ihecmetadata/filter/__init__.py
epigeec_ihecmetadata/filter/browserfilter.py
epigeec_ihecmetadata/ihecjson/__init__.py
epigeec_ihecmetadata/ihecjson/decoder.py
epigeec_ihecmetadata/ihecjson/encoder.py
epigeec_ihecmetadata-0.1.0.dist-info/LICENSE
epigeec_ihecmetadata-0.1.0.dist-info/METADATA
epigeec_ihecmetadata-0.1.0.dist-info/WHEEL
epigeec_ihecmetadata-0.1.0.dist-info/top_level.txt
epigeec_ihecmetadata-0.1.0.dist-info/RECORD
